fsm.v
module fsm(
    input clk,
    input rst_n,
    input q0,
    output reg load_registers,
    output reg add,
    output reg shift
);

localparam [3:0]
    initialize_registers = 3'b000,
    check_q0 = 3'b001,
    addition = 3'b010,
    shift_right = 3'b011,
    down_count = 3'b100,
    check_n = 3'b101,
    final = 3'b110;

reg [7:0] N;
reg [3:0] st, st_nxt;

always @(posedge clk, negedge rst_n) begin
    if(rst_n == 1'b0)
        st <= initialize_registers;
    else
        st <= st_nxt;
end

always @(*) begin
    case(st)
        initialize_registers:
            begin
                $display("initializez, %d",N);
                add = 1'b0;
                load_registers = 1'b1;
                shift = 1'b0;
                N = 8;
                st_nxt = check_q0;
            end
        check_q0:
            begin
                $display("verific q0, %d",N);
                add = 1'b0;
                load_registers = 1'b0;
                shift = 1'b0;
                if(q0 == 1'b1)
                    st_nxt = addition;
                else
                    st_nxt = shift_right;
            end
        addition:
            begin
                $display("adun, %d",N);
                add = 1'b1;
                load_registers = 1'b0;
                shift = 1'b0;
                st_nxt = shift_right;
            end
        shift_right:
            begin
                $display("shiftez, %d",N);
                add = 1'b0;
                load_registers = 1'b0;
                shift = 1'b1;
                st_nxt = down_count;
            end
        down_count:
            begin
                $display("decrementez, %d",N);
                add = 1'b0;
                load_registers = 1'b0;
                shift = 1'b0;
                N = N - 1;
                st_nxt = check_n;
            end
        check_n:
            begin
                $display("verfic N, %d",N);
                add = 1'b0;
                load_registers = 1'b0;
                shift = 1'b0;
                if(N == 0)
                    st_nxt = final;
                else
                    st_nxt = check_q0;
            end
        final:
            begin
                $display("final, %d",N);
                add = 1'b0;
                load_registers = 1'b0;
                shift = 1'b0;
                st_nxt = final;
            end
    endcase
end

endmodule

registers.v
module registers(
    input clk, rst_n,
    input load_registers, shift,
    input [7:0] eX,Y,
    output reg [7:0] A, B, Q
);

always @(posedge clk, negedge rst_n)
begin
    if(rst_n == 1'b0)
        {A,B,Q} <= 0;
    else if(load_registers == 1'b1)
        begin
            B <= eX;
            Q <= Y;
            A <= 0;
        end
    else if(shift == 1'b1)
        {A,Q} <= {1'b0,A,Q[7:1]};
end

endmodule

sum.v
module sum(
    input add,
    input [7:0] B,
    output reg [7:0] A
);

always @(add)
begin
    if(add)
        A = A + B;
end

endmodule

mul.v
`include "fsm.v"
`include "registers.v"
`include "sum.v"

module mul(
    input clk, rst_n,
    input [7:0] eX, Y,
    output [7:0] A, Q
);

wire add, load_registers, shift;
wire [7:0] B;

sum i0(
    .add(add),
    .B(B),
    .A(A));

registers i1(
    .clk(clk),
    .rst_n(rst_n),
    .load_registers(load_registers),
    .shift(shift),
    .eX(eX),
    .Y(Y),
    .A(A),
    .B(B),
    .Q(Q)
);

fsm i2(
    .clk(clk),
    .rst_n(rst_n),
    .q0(Q[0]),
    .load_registers(load_registers),
    .add(add),
    .shift(shift)
);

endmodule

mul_tb.v
`timescale 1ps/1ps
`include "mul.v"

module mul_tb;

reg clk, rst_n;
reg [7:0] eX, Y;
wire [7:0] A, Q;

mul cut(
    .clk(clk), .rst_n(rst_n),
    .eX(eX), .Y(Y),
    .A(A), .Q(Q)
);

initial begin
    clk = 1'b0;
    repeat (100)
    #5 clk = ~clk;
end

initial begin
    rst_n = 1'b0;
    #6 rst_n = 1'b1;
end

initial begin
    eX = 8'b00000011;
    Y  = 8'b00000010;
end

initial begin
    $dumpfile("test.vcd");
    $dumpvars(0,mul_tb);
end

endmodule

test.vcd
$date
	Mon Jun  5 15:12:26 2023
$end
$version
	Icarus Verilog
$end
$timescale
	1ps
$end
$scope module mul_tb $end
$var wire 8 ! A [7:0] $end
$var wire 8 " Q [7:0] $end
$var reg 8 # Y [7:0] $end
$var reg 1 $ clk $end
$var reg 8 % eX [7:0] $end
$var reg 1 & rst_n $end
$scope module cut $end
$var wire 8 ' A [7:0] $end
$var wire 8 ( Y [7:0] $end
$var wire 1 $ clk $end
$var wire 8 ) eX [7:0] $end
$var wire 1 & rst_n $end
$var wire 1 * shift $end
$var wire 1 + load_registers $end
$var wire 1 , add $end
$var wire 8 - Q [7:0] $end
$var wire 8 . B [7:0] $end
$scope module i0 $end
$var wire 1 , add $end
$var wire 8 / B [7:0] $end
$var reg 8 0 A [7:0] $end
$upscope $end
$scope module i1 $end
$var wire 8 1 Y [7:0] $end
$var wire 1 $ clk $end
$var wire 8 2 eX [7:0] $end
$var wire 1 & rst_n $end
$var wire 1 * shift $end
$var wire 1 + load_registers $end
$var reg 8 3 A [7:0] $end
$var reg 8 4 B [7:0] $end
$var reg 8 5 Q [7:0] $end
$upscope $end
$scope module i2 $end
$var wire 1 $ clk $end
$var wire 1 6 q0 $end
$var wire 1 & rst_n $end
$var reg 8 7 N [7:0] $end
$var reg 1 , add $end
$var reg 1 + load_registers $end
$var reg 1 * shift $end
$var reg 4 8 st [3:0] $end
$var reg 4 9 st_nxt [3:0] $end
$upscope $end
$upscope $end
$upscope $end
$enddefinitions $end
#0
$dumpvars
b1 9
b0 8
b1000 7
06
b0 5
b0 4
b0 3
b11 2
b10 1
bx 0
b0 /
b0 .
b0 -
0,
1+
0*
b11 )
b10 (
bx '
0&
b11 %
0$
b10 #
b0 "
bx !
$end
#5
1$
#6
1&
#10
0$
#15
b11 9
0+
b10 "
b10 -
b10 5
b11 .
b11 /
b11 4
b1 8
1$
#20
0$
#25
b100 9
1*
b11 8
1$
#30
0$
#35
16
b101 9
b110 7
0*
b1 "
b1 -
b1 5
b100 8
1$
#40
0$
#45
b1 9
b101 8
1$
#50
0$
#55
b10 9
b1 8
1$
#60
0$
#65
b11 9
1,
b10 8
1$
#70
0$
#75
b100 9
1*
0,
b11 8
1$
#80
0$
#85
b101 9
b101 7
0*
06
b100 8
b0 "
b0 -
b0 5
1$
#90
0$
#95
b1 9
b101 8
1$
#100
0$
#105
b11 9
b1 8
1$
#110
0$
#115
b100 9
1*
b11 8
1$
#120
0$
#125
b101 9
b100 7
0*
b100 8
1$
#130
0$
#135
b1 9
b101 8
1$
#140
0$
#145
b11 9
b1 8
1$
#150
0$
#155
b100 9
1*
b11 8
1$
#160
0$
#165
b101 9
b11 7
0*
b100 8
1$
#170
0$
#175
b1 9
b101 8
1$
#180
0$
#185
b11 9
b1 8
1$
#190
0$
#195
b100 9
1*
b11 8
1$
#200
0$
#205
b101 9
b10 7
0*
b100 8
1$
#210
0$
#215
b1 9
b101 8
1$
#220
0$
#225
b11 9
b1 8
1$
#230
0$
#235
b100 9
1*
b11 8
1$
#240
0$
#245
b101 9
b1 7
0*
b100 8
1$
#250
0$
#255
b1 9
b101 8
1$
#260
0$
#265
b11 9
b1 8
1$
#270
0$
#275
b100 9
1*
b11 8
1$
#280
0$
#285
b101 9
b0 7
0*
b100 8
1$
#290
0$
#295
b110 9
b101 8
1$
#300
0$
#305
b110 8
1$
